{"v":"5.12.1","fr":30,"ip":0,"op":32,"w":750,"h":750,"nm":"Card 2","ddd":0,"assets":[],"layers":[{"ddd":0,"ind":1,"ty":4,"nm":"card Outlines 4","sr":1,"ks":{"o":{"a":1,"k":[{"i":{"x":[0.667],"y":[1]},"o":{"x":[0.333],"y":[0]},"t":22,"s":[0]},{"t":30,"s":[100]}],"ix":11},"r":{"a":1,"k":[{"i":{"x":[0.833],"y":[1]},"o":{"x":[0.167],"y":[0]},"t":0,"s":[0]},{"i":{"x":[0.833],"y":[1.057]},"o":{"x":[0.167],"y":[0]},"t":0.5,"s":[0]},{"i":{"x":[0.833],"y":[0.693]},"o":{"x":[0.167],"y":[0.083]},"t":1,"s":[0]},{"i":{"x":[0.833],"y":[0.796]},"o":{"x":[0.167],"y":[0.114]},"t":1.5,"s":[-0.686]},{"i":{"x":[0.833],"y":[0.818]},"o":{"x":[0.167],"y":[0.141]},"t":2,"s":[-2.524]},{"i":{"x":[0.833],"y":[0.829]},"o":{"x":[0.167],"y":[0.154]},"t":2.5,"s":[-5.185]},{"i":{"x":[0.833],"y":[0.837]},"o":{"x":[0.167],"y":[0.163]},"t":3,"s":[-8.34]},{"i":{"x":[0.833],"y":[0.846]},"o":{"x":[0.167],"y":[0.171]},"t":3.5,"s":[-11.66]},{"i":{"x":[0.833],"y":[0.859]},"o":{"x":[0.167],"y":[0.182]},"t":4,"s":[-14.815]},{"i":{"x":[0.833],"y":[0.886]},"o":{"x":[0.167],"y":[0.204]},"t":4.5,"s":[-17.476]},{"i":{"x":[0.833],"y":[1.093]},"o":{"x":[0.167],"y":[0.307]},"t":5,"s":[-19.314]},{"i":{"x":[0.833],"y":[0.719]},"o":{"x":[0.167],"y":[0.044]},"t":5.5,"s":[-20]},{"i":{"x":[0.833],"y":[0.806]},"o":{"x":[0.167],"y":[0.118]},"t":6,"s":[-18.547]},{"i":{"x":[0.833],"y":[0.822]},"o":{"x":[0.167],"y":[0.146]},"t":6.5,"s":[-15.101]},{"i":{"x":[0.833],"y":[0.836]},"o":{"x":[0.167],"y":[0.157]},"t":7,"s":[-10.526]},{"i":{"x":[0.833],"y":[0.875]},"o":{"x":[0.167],"y":[0.169]},"t":7.5,"s":[-5.323]},{"i":{"x":[0.833],"y":[0.848]},"o":{"x":[0.167],"y":[0.248]},"t":8,"s":[-0.276]},{"i":{"x":[0.833],"y":[0.85]},"o":{"x":[0.167],"y":[0.185]},"t":8.5,"s":[2.274]},{"i":{"x":[0.833],"y":[0.852]},"o":{"x":[0.167],"y":[0.188]},"t":9,"s":[4.362]},{"i":{"x":[0.833],"y":[0.855]},"o":{"x":[0.167],"y":[0.191]},"t":9.5,"s":[6.027]},{"i":{"x":[0.833],"y":[0.86]},"o":{"x":[0.167],"y":[0.197]},"t":10,"s":[7.31]},{"i":{"x":[0.833],"y":[0.867]},"o":{"x":[0.167],"y":[0.206]},"t":10.5,"s":[8.253]},{"i":{"x":[0.833],"y":[0.883]},"o":{"x":[0.167],"y":[0.224]},"t":11,"s":[8.895]},{"i":{"x":[0.833],"y":[0.936]},"o":{"x":[0.167],"y":[0.288]},"t":11.5,"s":[9.275]},{"i":{"x":[0.833],"y":[0.469]},"o":{"x":[0.167],"y":[-0.272]},"t":12,"s":[9.429]},{"i":{"x":[0.833],"y":[0.778]},"o":{"x":[0.167],"y":[0.099]},"t":12.5,"s":[9.393]},{"i":{"x":[0.833],"y":[0.807]},"o":{"x":[0.167],"y":[0.133]},"t":13,"s":[9.198]},{"i":{"x":[0.833],"y":[0.818]},"o":{"x":[0.167],"y":[0.147]},"t":13.5,"s":[8.875]},{"i":{"x":[0.833],"y":[0.824]},"o":{"x":[0.167],"y":[0.154]},"t":14,"s":[8.449]},{"i":{"x":[0.833],"y":[0.828]},"o":{"x":[0.167],"y":[0.158]},"t":14.5,"s":[7.946]},{"i":{"x":[0.833],"y":[0.83]},"o":{"x":[0.167],"y":[0.162]},"t":15,"s":[7.388]},{"i":{"x":[0.833],"y":[0.833]},"o":{"x":[0.167],"y":[0.164]},"t":15.5,"s":[6.792]},{"i":{"x":[0.833],"y":[0.834]},"o":{"x":[0.167],"y":[0.166]},"t":16,"s":[6.177]},{"i":{"x":[0.833],"y":[0.835]},"o":{"x":[0.167],"y":[0.167]},"t":16.5,"s":[5.555]},{"i":{"x":[0.833],"y":[0.837]},"o":{"x":[0.167],"y":[0.169]},"t":17,"s":[4.939]},{"i":{"x":[0.833],"y":[0.838]},"o":{"x":[0.167],"y":[0.17]},"t":17.5,"s":[4.339]},{"i":{"x":[0.833],"y":[0.839]},"o":{"x":[0.167],"y":[0.171]},"t":18,"s":[3.762]},{"i":{"x":[0.833],"y":[0.839]},"o":{"x":[0.167],"y":[0.172]},"t":18.5,"s":[3.215]},{"i":{"x":[0.833],"y":[0.84]},"o":{"x":[0.167],"y":[0.173]},"t":19,"s":[2.702]},{"i":{"x":[0.833],"y":[0.841]},"o":{"x":[0.167],"y":[0.174]},"t":19.5,"s":[2.227]},{"i":{"x":[0.833],"y":[0.842]},"o":{"x":[0.167],"y":[0.175]},"t":20,"s":[1.792]},{"i":{"x":[0.833],"y":[0.843]},"o":{"x":[0.167],"y":[0.176]},"t":20.5,"s":[1.397]},{"i":{"x":[0.833],"y":[0.844]},"o":{"x":[0.167],"y":[0.177]},"t":21,"s":[1.044]},{"i":{"x":[0.833],"y":[0.845]},"o":{"x":[0.167],"y":[0.179]},"t":21.5,"s":[0.73]},{"i":{"x":[0.833],"y":[0.846]},"o":{"x":[0.167],"y":[0.18]},"t":22,"s":[0.456]},{"i":{"x":[0.833],"y":[0.847]},"o":{"x":[0.167],"y":[0.181]},"t":22.5,"s":[0.219]},{"i":{"x":[0.833],"y":[0.848]},"o":{"x":[0.167],"y":[0.183]},"t":23,"s":[0.018]},{"i":{"x":[0.833],"y":[0.85]},"o":{"x":[0.167],"y":[0.185]},"t":23.5,"s":[-0.15]},{"i":{"x":[0.833],"y":[0.852]},"o":{"x":[0.167],"y":[0.188]},"t":24,"s":[-0.288]},{"i":{"x":[0.833],"y":[0.855]},"o":{"x":[0.167],"y":[0.191]},"t":24.5,"s":[-0.398]},{"i":{"x":[0.833],"y":[0.86]},"o":{"x":[0.167],"y":[0.197]},"t":25,"s":[-0.482]},{"i":{"x":[0.833],"y":[0.867]},"o":{"x":[0.167],"y":[0.206]},"t":25.5,"s":[-0.545]},{"i":{"x":[0.833],"y":[0.883]},"o":{"x":[0.167],"y":[0.224]},"t":26,"s":[-0.587]},{"i":{"x":[0.833],"y":[0.936]},"o":{"x":[0.167],"y":[0.288]},"t":26.5,"s":[-0.612]},{"i":{"x":[0.833],"y":[0.469]},"o":{"x":[0.167],"y":[-0.272]},"t":27,"s":[-0.622]},{"i":{"x":[0.833],"y":[0.778]},"o":{"x":[0.167],"y":[0.099]},"t":27.5,"s":[-0.62]},{"i":{"x":[0.833],"y":[0.807]},"o":{"x":[0.167],"y":[0.133]},"t":28,"s":[-0.607]},{"i":{"x":[0.833],"y":[0.818]},"o":{"x":[0.167],"y":[0.147]},"t":28.5,"s":[-0.586]},{"i":{"x":[0.833],"y":[0.824]},"o":{"x":[0.167],"y":[0.154]},"t":29,"s":[-0.558]},{"i":{"x":[0.833],"y":[0.828]},"o":{"x":[0.167],"y":[0.158]},"t":29.5,"s":[-0.524]},{"i":{"x":[0.833],"y":[0.83]},"o":{"x":[0.167],"y":[0.162]},"t":30,"s":[-0.488]},{"i":{"x":[0.833],"y":[0.833]},"o":{"x":[0.167],"y":[0.164]},"t":30.5,"s":[-0.448]},{"i":{"x":[0.833],"y":[0.834]},"o":{"x":[0.167],"y":[0.166]},"t":31,"s":[-0.408]},{"i":{"x":[0.833],"y":[0.833]},"o":{"x":[0.167],"y":[0.167]},"t":31.5,"s":[-0.367]},{"t":32,"s":[-0.326]}],"ix":10},"p":{"a":0,"k":[375,237.036,0],"ix":2,"l":2},"a":{"a":0,"k":[226.881,21.604,0],"ix":1,"l":2},"s":{"a":1,"k":[{"i":{"x":[0.833,0.833,0.833],"y":[1,1,1]},"o":{"x":[0.167,0.167,0.167],"y":[0,0,0]},"t":0,"s":[1644,1644,100]},{"i":{"x":[0.833,0.833,0.833],"y":[1.126,1.126,1]},"o":{"x":[0.167,0.167,0.167],"y":[0,0,0]},"t":0.5,"s":[1644,1644,100]},{"i":{"x":[0.833,0.833,0.833],"y":[0.693,0.693,1]},"o":{"x":[0.167,0.167,0.167],"y":[0.083,0.083,0]},"t":1,"s":[1644,1644,100]},{"i":{"x":[0.833,0.833,0.833],"y":[0.796,0.796,1]},"o":{"x":[0.167,0.167,0.167],"y":[0.114,0.114,0]},"t":1.5,"s":[1642.491,1642.491,100]},{"i":{"x":[0.833,0.833,0.833],"y":[0.818,0.818,1]},"o":{"x":[0.167,0.167,0.167],"y":[0.141,0.141,0]},"t":2,"s":[1638.447,1638.447,100]},{"i":{"x":[0.833,0.833,0.833],"y":[0.829,0.829,1]},"o":{"x":[0.167,0.167,0.167],"y":[0.154,0.154,0]},"t":2.5,"s":[1632.593,1632.593,100]},{"i":{"x":[0.833,0.833,0.833],"y":[0.837,0.837,1]},"o":{"x":[0.167,0.167,0.167],"y":[0.163,0.163,0]},"t":3,"s":[1625.652,1625.652,100]},{"i":{"x":[0.833,0.833,0.833],"y":[0.846,0.846,1]},"o":{"x":[0.167,0.167,0.167],"y":[0.171,0.171,0]},"t":3.5,"s":[1618.348,1618.348,100]},{"i":{"x":[0.833,0.833,0.833],"y":[0.859,0.859,1]},"o":{"x":[0.167,0.167,0.167],"y":[0.182,0.182,0]},"t":4,"s":[1611.407,1611.407,100]},{"i":{"x":[0.833,0.833,0.833],"y":[0.886,0.886,1]},"o":{"x":[0.167,0.167,0.167],"y":[0.204,0.204,0]},"t":4.5,"s":[1605.553,1605.553,100]},{"i":{"x":[0.833,0.833,0.833],"y":[1.093,1.093,1]},"o":{"x":[0.167,0.167,0.167],"y":[0.307,0.307,0]},"t":5,"s":[1601.509,1601.509,100]},{"i":{"x":[0.833,0.833,0.833],"y":[0.719,0.719,1]},"o":{"x":[0.167,0.167,0.167],"y":[0.044,0.044,0]},"t":5.5,"s":[1600,1600,100]},{"i":{"x":[0.833,0.833,0.833],"y":[0.806,0.806,1]},"o":{"x":[0.167,0.167,0.167],"y":[0.118,0.118,0]},"t":6,"s":[1603.196,1603.196,100]},{"i":{"x":[0.833,0.833,0.833],"y":[0.822,0.822,1]},"o":{"x":[0.167,0.167,0.167],"y":[0.146,0.146,0]},"t":6.5,"s":[1610.778,1610.778,100]},{"i":{"x":[0.833,0.833,0.833],"y":[0.836,0.836,1]},"o":{"x":[0.167,0.167,0.167],"y":[0.157,0.157,0]},"t":7,"s":[1620.844,1620.844,100]},{"i":{"x":[0.833,0.833,0.833],"y":[0.875,0.875,1]},"o":{"x":[0.167,0.167,0.167],"y":[0.169,0.169,0]},"t":7.5,"s":[1632.289,1632.289,100]},{"i":{"x":[0.833,0.833,0.833],"y":[0.848,0.848,1]},"o":{"x":[0.167,0.167,0.167],"y":[0.248,0.248,0]},"t":8,"s":[1643.394,1643.394,100]},{"i":{"x":[0.833,0.833,0.833],"y":[0.85,0.85,1]},"o":{"x":[0.167,0.167,0.167],"y":[0.185,0.185,0]},"t":8.5,"s":[1649.003,1649.003,100]},{"i":{"x":[0.833,0.833,0.833],"y":[0.852,0.852,1]},"o":{"x":[0.167,0.167,0.167],"y":[0.188,0.188,0]},"t":9,"s":[1653.595,1653.595,100]},{"i":{"x":[0.833,0.833,0.833],"y":[0.855,0.855,1]},"o":{"x":[0.167,0.167,0.167],"y":[0.191,0.191,0]},"t":9.5,"s":[1657.258,1657.258,100]},{"i":{"x":[0.833,0.833,0.833],"y":[0.86,0.86,1]},"o":{"x":[0.167,0.167,0.167],"y":[0.197,0.197,0]},"t":10,"s":[1660.082,1660.082,100]},{"i":{"x":[0.833,0.833,0.833],"y":[0.867,0.867,1]},"o":{"x":[0.167,0.167,0.167],"y":[0.206,0.206,0]},"t":10.5,"s":[1662.156,1662.156,100]},{"i":{"x":[0.833,0.833,0.833],"y":[0.883,0.883,1]},"o":{"x":[0.167,0.167,0.167],"y":[0.224,0.224,0]},"t":11,"s":[1663.568,1663.568,100]},{"i":{"x":[0.833,0.833,0.833],"y":[0.936,0.936,1]},"o":{"x":[0.167,0.167,0.167],"y":[0.288,0.288,0]},"t":11.5,"s":[1664.404,1664.404,100]},{"i":{"x":[0.833,0.833,0.833],"y":[0.469,0.469,1]},"o":{"x":[0.167,0.167,0.167],"y":[-0.272,-0.272,0]},"t":12,"s":[1664.744,1664.744,100]},{"i":{"x":[0.833,0.833,0.833],"y":[0.778,0.778,1]},"o":{"x":[0.167,0.167,0.167],"y":[0.099,0.099,0]},"t":12.5,"s":[1664.664,1664.664,100]},{"i":{"x":[0.833,0.833,0.833],"y":[0.807,0.807,1]},"o":{"x":[0.167,0.167,0.167],"y":[0.133,0.133,0]},"t":13,"s":[1664.236,1664.236,100]},{"i":{"x":[0.833,0.833,0.833],"y":[0.818,0.818,1]},"o":{"x":[0.167,0.167,0.167],"y":[0.147,0.147,0]},"t":13.5,"s":[1663.524,1663.524,100]},{"i":{"x":[0.833,0.833,0.833],"y":[0.824,0.824,1]},"o":{"x":[0.167,0.167,0.167],"y":[0.154,0.154,0]},"t":14,"s":[1662.588,1662.588,100]},{"i":{"x":[0.833,0.833,0.833],"y":[0.828,0.828,1]},"o":{"x":[0.167,0.167,0.167],"y":[0.158,0.158,0]},"t":14.5,"s":[1661.482,1661.482,100]},{"i":{"x":[0.833,0.833,0.833],"y":[0.83,0.83,1]},"o":{"x":[0.167,0.167,0.167],"y":[0.162,0.162,0]},"t":15,"s":[1660.253,1660.253,100]},{"i":{"x":[0.833,0.833,0.833],"y":[0.833,0.833,1]},"o":{"x":[0.167,0.167,0.167],"y":[0.164,0.164,0]},"t":15.5,"s":[1658.943,1658.943,100]},{"i":{"x":[0.833,0.833,0.833],"y":[0.834,0.834,1]},"o":{"x":[0.167,0.167,0.167],"y":[0.166,0.166,0]},"t":16,"s":[1657.589,1657.589,100]},{"i":{"x":[0.833,0.833,0.833],"y":[0.835,0.835,1]},"o":{"x":[0.167,0.167,0.167],"y":[0.167,0.167,0]},"t":16.5,"s":[1656.221,1656.221,100]},{"i":{"x":[0.833,0.833,0.833],"y":[0.837,0.837,1]},"o":{"x":[0.167,0.167,0.167],"y":[0.169,0.169,0]},"t":17,"s":[1654.866,1654.866,100]},{"i":{"x":[0.833,0.833,0.833],"y":[0.838,0.838,1]},"o":{"x":[0.167,0.167,0.167],"y":[0.17,0.17,0]},"t":17.5,"s":[1653.545,1653.545,100]},{"i":{"x":[0.833,0.833,0.833],"y":[0.839,0.839,1]},"o":{"x":[0.167,0.167,0.167],"y":[0.171,0.171,0]},"t":18,"s":[1652.276,1652.276,100]},{"i":{"x":[0.833,0.833,0.833],"y":[0.839,0.839,1]},"o":{"x":[0.167,0.167,0.167],"y":[0.172,0.172,0]},"t":18.5,"s":[1651.073,1651.073,100]},{"i":{"x":[0.833,0.833,0.833],"y":[0.84,0.84,1]},"o":{"x":[0.167,0.167,0.167],"y":[0.173,0.173,0]},"t":19,"s":[1649.945,1649.945,100]},{"i":{"x":[0.833,0.833,0.833],"y":[0.841,0.841,1]},"o":{"x":[0.167,0.167,0.167],"y":[0.174,0.174,0]},"t":19.5,"s":[1648.9,1648.9,100]},{"i":{"x":[0.833,0.833,0.833],"y":[0.842,0.842,1]},"o":{"x":[0.167,0.167,0.167],"y":[0.175,0.175,0]},"t":20,"s":[1647.942,1647.942,100]},{"i":{"x":[0.833,0.833,0.833],"y":[0.843,0.843,1]},"o":{"x":[0.167,0.167,0.167],"y":[0.176,0.176,0]},"t":20.5,"s":[1647.074,1647.074,100]},{"i":{"x":[0.833,0.833,0.833],"y":[0.844,0.844,1]},"o":{"x":[0.167,0.167,0.167],"y":[0.177,0.177,0]},"t":21,"s":[1646.296,1646.296,100]},{"i":{"x":[0.833,0.833,0.833],"y":[0.845,0.845,1]},"o":{"x":[0.167,0.167,0.167],"y":[0.179,0.179,0]},"t":21.5,"s":[1645.607,1645.607,100]},{"i":{"x":[0.833,0.833,0.833],"y":[0.846,0.846,1]},"o":{"x":[0.167,0.167,0.167],"y":[0.18,0.18,0]},"t":22,"s":[1645.004,1645.004,100]},{"i":{"x":[0.833,0.833,0.833],"y":[0.847,0.847,1]},"o":{"x":[0.167,0.167,0.167],"y":[0.181,0.181,0]},"t":22.5,"s":[1644.483,1644.483,100]},{"i":{"x":[0.833,0.833,0.833],"y":[0.848,0.848,1]},"o":{"x":[0.167,0.167,0.167],"y":[0.183,0.183,0]},"t":23,"s":[1644.04,1644.04,100]},{"i":{"x":[0.833,0.833,0.833],"y":[0.85,0.85,1]},"o":{"x":[0.167,0.167,0.167],"y":[0.185,0.185,0]},"t":23.5,"s":[1643.67,1643.67,100]},{"i":{"x":[0.833,0.833,0.833],"y":[0.852,0.852,1]},"o":{"x":[0.167,0.167,0.167],"y":[0.188,0.188,0]},"t":24,"s":[1643.367,1643.367,100]},{"i":{"x":[0.833,0.833,0.833],"y":[0.855,0.855,1]},"o":{"x":[0.167,0.167,0.167],"y":[0.191,0.191,0]},"t":24.5,"s":[1643.125,1643.125,100]},{"i":{"x":[0.833,0.833,0.833],"y":[0.86,0.86,1]},"o":{"x":[0.167,0.167,0.167],"y":[0.197,0.197,0]},"t":25,"s":[1642.939,1642.939,100]},{"i":{"x":[0.833,0.833,0.833],"y":[0.867,0.867,1]},"o":{"x":[0.167,0.167,0.167],"y":[0.206,0.206,0]},"t":25.5,"s":[1642.802,1642.802,100]},{"i":{"x":[0.833,0.833,0.833],"y":[0.883,0.883,1]},"o":{"x":[0.167,0.167,0.167],"y":[0.224,0.224,0]},"t":26,"s":[1642.709,1642.709,100]},{"i":{"x":[0.833,0.833,0.833],"y":[0.936,0.936,1]},"o":{"x":[0.167,0.167,0.167],"y":[0.288,0.288,0]},"t":26.5,"s":[1642.654,1642.654,100]},{"i":{"x":[0.833,0.833,0.833],"y":[0.469,0.469,1]},"o":{"x":[0.167,0.167,0.167],"y":[-0.272,-0.272,0]},"t":27,"s":[1642.631,1642.631,100]},{"i":{"x":[0.833,0.833,0.833],"y":[0.778,0.778,1]},"o":{"x":[0.167,0.167,0.167],"y":[0.099,0.099,0]},"t":27.5,"s":[1642.636,1642.636,100]},{"i":{"x":[0.833,0.833,0.833],"y":[0.807,0.807,1]},"o":{"x":[0.167,0.167,0.167],"y":[0.133,0.133,0]},"t":28,"s":[1642.665,1642.665,100]},{"i":{"x":[0.833,0.833,0.833],"y":[0.818,0.818,1]},"o":{"x":[0.167,0.167,0.167],"y":[0.147,0.147,0]},"t":28.5,"s":[1642.712,1642.712,100]},{"i":{"x":[0.833,0.833,0.833],"y":[0.824,0.824,1]},"o":{"x":[0.167,0.167,0.167],"y":[0.154,0.154,0]},"t":29,"s":[1642.773,1642.773,100]},{"i":{"x":[0.833,0.833,0.833],"y":[0.828,0.828,1]},"o":{"x":[0.167,0.167,0.167],"y":[0.158,0.158,0]},"t":29.5,"s":[1642.846,1642.846,100]},{"i":{"x":[0.833,0.833,0.833],"y":[0.83,0.83,1]},"o":{"x":[0.167,0.167,0.167],"y":[0.162,0.162,0]},"t":30,"s":[1642.927,1642.927,100]},{"i":{"x":[0.833,0.833,0.833],"y":[0.833,0.833,1]},"o":{"x":[0.167,0.167,0.167],"y":[0.164,0.164,0]},"t":30.5,"s":[1643.014,1643.014,100]},{"i":{"x":[0.833,0.833,0.833],"y":[0.834,0.834,1]},"o":{"x":[0.167,0.167,0.167],"y":[0.166,0.166,0]},"t":31,"s":[1643.103,1643.103,100]},{"i":{"x":[0.833,0.833,0.833],"y":[0.833,0.833,1]},"o":{"x":[0.167,0.167,0.167],"y":[0.167,0.167,0]},"t":31.5,"s":[1643.194,1643.194,100]},{"t":32,"s":[1643.283,1643.283,100]}],"ix":6,"l":2}},"ao":0,"ef":[{"ty":5,"nm":"Elastic Controller","np":5,"mn":"Pseudo/MDS Elastic Controller","ix":1,"en":1,"ef":[{"ty":0,"nm":"Amplitude","mn":"Pseudo/MDS Elastic Controller-0001","ix":1,"v":{"a":0,"k":100,"ix":1}},{"ty":0,"nm":"Frequency","mn":"Pseudo/MDS Elastic Controller-0002","ix":2,"v":{"a":0,"k":100,"ix":2}},{"ty":0,"nm":"Decay","mn":"Pseudo/MDS Elastic Controller-0003","ix":3,"v":{"a":0,"k":100,"ix":3}}]},{"ty":5,"nm":"Elastic Controller 2","np":5,"mn":"Pseudo/MDS Elastic Controller","ix":2,"en":1,"ef":[{"ty":0,"nm":"Amplitude","mn":"Pseudo/MDS Elastic Controller-0001","ix":1,"v":{"a":0,"k":100,"ix":1}},{"ty":0,"nm":"Frequency","mn":"Pseudo/MDS Elastic Controller-0002","ix":2,"v":{"a":0,"k":100,"ix":2}},{"ty":0,"nm":"Decay","mn":"Pseudo/MDS Elastic Controller-0003","ix":3,"v":{"a":0,"k":100,"ix":3}}]}],"shapes":[{"ty":"gr","it":[{"ind":0,"ty":"sh","ix":1,"ks":{"a":0,"k":{"i":[[0,0],[0,0]],"o":[[0,0],[0,0]],"v":[[216.391,27.898],[237.371,27.898]],"c":false},"ix":2},"nm":"Path 1","mn":"ADBE Vector Shape - Group","hd":false},{"ty":"st","c":{"a":0,"k":[1,1,1,1],"ix":3},"o":{"a":0,"k":100,"ix":4},"w":{"a":0,"k":2,"ix":5},"lc":2,"lj":1,"ml":4,"bm":0,"nm":"Stroke 1","mn":"ADBE Vector Graphic - Stroke","hd":false},{"ty":"tr","p":{"a":0,"k":[0,1],"ix":2},"a":{"a":0,"k":[0,0],"ix":1},"s":{"a":0,"k":[100,100],"ix":3},"r":{"a":0,"k":0,"ix":6},"o":{"a":0,"k":100,"ix":7},"sk":{"a":0,"k":0,"ix":4},"sa":{"a":0,"k":0,"ix":5},"nm":"Transform"}],"nm":"Group 1","np":2,"cix":2,"bm":0,"ix":1,"mn":"ADBE Vector Group","hd":false},{"ty":"gr","it":[{"ind":0,"ty":"sh","ix":1,"ks":{"a":0,"k":{"i":[[0,3.956],[-1.229,1.229],[-3.956,0],[0,0],[-1.229,-1.229],[0,-3.956],[1.229,-1.229],[3.956,0],[0,0],[1.229,1.229]],"o":[[0,-3.956],[1.229,-1.229],[0,0],[3.956,0],[1.229,1.229],[0,3.956],[-1.229,1.229],[0,0],[-3.956,0],[-1.229,-1.229]],"v":[[-10.49,0],[-9.261,-7.163],[-2.098,-8.392],[2.098,-8.392],[9.261,-7.163],[10.49,0],[9.261,7.163],[2.098,8.392],[-2.098,8.392],[-9.261,7.163]],"c":true},"ix":2},"nm":"Path 1","mn":"ADBE Vector Shape - Group","hd":false},{"ty":"st","c":{"a":1,"k":[{"i":{"x":[0],"y":[1]},"o":{"x":[0.333],"y":[0]},"t":1,"s":[0.6,0.6,0.6,1]},{"i":{"x":[0.667],"y":[1]},"o":{"x":[1],"y":[0]},"t":9.5,"s":[0.580392181873,0.949019610882,0.498039215803,1]},{"i":{"x":[0.667],"y":[1]},"o":{"x":[0.167],"y":[0]},"t":18,"s":[0.6,0.6,0.6,1]},{"t":28.5,"s":[1,1,1,1]}],"ix":3},"o":{"a":0,"k":100,"ix":4},"w":{"a":0,"k":2,"ix":5},"lc":1,"lj":1,"ml":4,"bm":0,"nm":"Stroke 1","mn":"ADBE Vector Graphic - Stroke","hd":false},{"ty":"tr","p":{"a":0,"k":[226.881,29.996],"ix":2},"a":{"a":0,"k":[0,0],"ix":1},"s":{"a":0,"k":[100,100],"ix":3},"r":{"a":0,"k":0,"ix":6},"o":{"a":0,"k":100,"ix":7},"sk":{"a":0,"k":0,"ix":4},"sa":{"a":0,"k":0,"ix":5},"nm":"Transform"}],"nm":"Group 2","np":2,"cix":2,"bm":0,"ix":2,"mn":"ADBE Vector Group","hd":false},{"ty":"tm","s":{"a":0,"k":0,"ix":1},"e":{"a":0,"k":100,"ix":2},"o":{"a":0,"k":69,"ix":3},"m":1,"ix":3,"nm":"Trim Paths 2","mn":"ADBE Vector Filter - Trim","hd":false}],"ip":0,"op":32,"st":0,"ct":1,"bm":0},{"ddd":0,"ind":2,"ty":4,"nm":"card Outlines 2","parent":3,"sr":1,"ks":{"o":{"a":0,"k":100,"ix":11},"r":{"a":0,"k":0,"ix":10},"p":{"a":0,"k":[226.88,30.918,0],"ix":2,"l":2},"a":{"a":0,"k":[226.881,29.996,0],"ix":1,"l":2},"s":{"a":0,"k":[100,100,100],"ix":6,"l":2}},"ao":0,"shapes":[{"ty":"gr","it":[{"ind":0,"ty":"sh","ix":1,"ks":{"a":0,"k":{"i":[[0,0],[0,0]],"o":[[0,0],[0,0]],"v":[[216.391,27.898],[237.371,27.898]],"c":false},"ix":2},"nm":"Path 1","mn":"ADBE Vector Shape - Group","hd":false},{"ty":"st","c":{"a":1,"k":[{"i":{"x":[0],"y":[1]},"o":{"x":[0.333],"y":[0]},"t":1,"s":[0.6,0.6,0.6,1]},{"i":{"x":[0.667],"y":[1]},"o":{"x":[1],"y":[0]},"t":9.5,"s":[0.580392181873,0.949019610882,0.498039215803,1]},{"t":18,"s":[0.6,0.6,0.6,1]}],"ix":3},"o":{"a":0,"k":100,"ix":4},"w":{"a":0,"k":2,"ix":5},"lc":2,"lj":1,"ml":4,"bm":0,"nm":"Stroke 1","mn":"ADBE Vector Graphic - Stroke","hd":false},{"ty":"tr","p":{"a":0,"k":[0,0],"ix":2},"a":{"a":0,"k":[0,0],"ix":1},"s":{"a":0,"k":[100,100],"ix":3},"r":{"a":0,"k":0,"ix":6},"o":{"a":0,"k":100,"ix":7},"sk":{"a":0,"k":0,"ix":4},"sa":{"a":0,"k":0,"ix":5},"nm":"Transform"}],"nm":"Group 1","np":2,"cix":2,"bm":0,"ix":1,"mn":"ADBE Vector Group","hd":false},{"ty":"tm","s":{"a":1,"k":[{"i":{"x":[0.31],"y":[1]},"o":{"x":[0.69],"y":[0]},"t":0,"s":[0]},{"i":{"x":[0.833],"y":[1]},"o":{"x":[0.69],"y":[0]},"t":9.762,"s":[100]},{"i":{"x":[0.31],"y":[1]},"o":{"x":[0.167],"y":[0]},"t":10,"s":[0]},{"t":20.5,"s":[100]}],"ix":1},"e":{"a":1,"k":[{"i":{"x":[0.833],"y":[1]},"o":{"x":[0.167],"y":[0]},"t":9.762,"s":[100]},{"t":10,"s":[0]}],"ix":2},"o":{"a":0,"k":0,"ix":3},"m":1,"ix":3,"nm":"Trim Paths 2","mn":"ADBE Vector Filter - Trim","hd":false}],"ip":0,"op":32,"st":0,"ct":1,"bm":0},{"ddd":0,"ind":3,"ty":4,"nm":"card Outlines","sr":1,"ks":{"o":{"a":0,"k":100,"ix":11},"r":{"a":1,"k":[{"i":{"x":[0.833],"y":[1]},"o":{"x":[0.167],"y":[0]},"t":0,"s":[0]},{"i":{"x":[0.833],"y":[1.057]},"o":{"x":[0.167],"y":[0]},"t":0.5,"s":[0]},{"i":{"x":[0.833],"y":[0.693]},"o":{"x":[0.167],"y":[0.083]},"t":1,"s":[0]},{"i":{"x":[0.833],"y":[0.796]},"o":{"x":[0.167],"y":[0.114]},"t":1.5,"s":[-0.686]},{"i":{"x":[0.833],"y":[0.818]},"o":{"x":[0.167],"y":[0.141]},"t":2,"s":[-2.524]},{"i":{"x":[0.833],"y":[0.829]},"o":{"x":[0.167],"y":[0.154]},"t":2.5,"s":[-5.185]},{"i":{"x":[0.833],"y":[0.837]},"o":{"x":[0.167],"y":[0.163]},"t":3,"s":[-8.34]},{"i":{"x":[0.833],"y":[0.846]},"o":{"x":[0.167],"y":[0.171]},"t":3.5,"s":[-11.66]},{"i":{"x":[0.833],"y":[0.859]},"o":{"x":[0.167],"y":[0.182]},"t":4,"s":[-14.815]},{"i":{"x":[0.833],"y":[0.886]},"o":{"x":[0.167],"y":[0.204]},"t":4.5,"s":[-17.476]},{"i":{"x":[0.833],"y":[1.093]},"o":{"x":[0.167],"y":[0.307]},"t":5,"s":[-19.314]},{"i":{"x":[0.833],"y":[0.719]},"o":{"x":[0.167],"y":[0.044]},"t":5.5,"s":[-20]},{"i":{"x":[0.833],"y":[0.806]},"o":{"x":[0.167],"y":[0.118]},"t":6,"s":[-18.547]},{"i":{"x":[0.833],"y":[0.822]},"o":{"x":[0.167],"y":[0.146]},"t":6.5,"s":[-15.101]},{"i":{"x":[0.833],"y":[0.836]},"o":{"x":[0.167],"y":[0.157]},"t":7,"s":[-10.526]},{"i":{"x":[0.833],"y":[0.875]},"o":{"x":[0.167],"y":[0.169]},"t":7.5,"s":[-5.323]},{"i":{"x":[0.833],"y":[0.848]},"o":{"x":[0.167],"y":[0.248]},"t":8,"s":[-0.276]},{"i":{"x":[0.833],"y":[0.85]},"o":{"x":[0.167],"y":[0.185]},"t":8.5,"s":[2.274]},{"i":{"x":[0.833],"y":[0.852]},"o":{"x":[0.167],"y":[0.188]},"t":9,"s":[4.362]},{"i":{"x":[0.833],"y":[0.855]},"o":{"x":[0.167],"y":[0.191]},"t":9.5,"s":[6.027]},{"i":{"x":[0.833],"y":[0.86]},"o":{"x":[0.167],"y":[0.197]},"t":10,"s":[7.31]},{"i":{"x":[0.833],"y":[0.867]},"o":{"x":[0.167],"y":[0.206]},"t":10.5,"s":[8.253]},{"i":{"x":[0.833],"y":[0.883]},"o":{"x":[0.167],"y":[0.224]},"t":11,"s":[8.895]},{"i":{"x":[0.833],"y":[0.936]},"o":{"x":[0.167],"y":[0.288]},"t":11.5,"s":[9.275]},{"i":{"x":[0.833],"y":[0.469]},"o":{"x":[0.167],"y":[-0.272]},"t":12,"s":[9.429]},{"i":{"x":[0.833],"y":[0.778]},"o":{"x":[0.167],"y":[0.099]},"t":12.5,"s":[9.393]},{"i":{"x":[0.833],"y":[0.807]},"o":{"x":[0.167],"y":[0.133]},"t":13,"s":[9.198]},{"i":{"x":[0.833],"y":[0.818]},"o":{"x":[0.167],"y":[0.147]},"t":13.5,"s":[8.875]},{"i":{"x":[0.833],"y":[0.824]},"o":{"x":[0.167],"y":[0.154]},"t":14,"s":[8.449]},{"i":{"x":[0.833],"y":[0.828]},"o":{"x":[0.167],"y":[0.158]},"t":14.5,"s":[7.946]},{"i":{"x":[0.833],"y":[0.83]},"o":{"x":[0.167],"y":[0.162]},"t":15,"s":[7.388]},{"i":{"x":[0.833],"y":[0.833]},"o":{"x":[0.167],"y":[0.164]},"t":15.5,"s":[6.792]},{"i":{"x":[0.833],"y":[0.834]},"o":{"x":[0.167],"y":[0.166]},"t":16,"s":[6.177]},{"i":{"x":[0.833],"y":[0.835]},"o":{"x":[0.167],"y":[0.167]},"t":16.5,"s":[5.555]},{"i":{"x":[0.833],"y":[0.837]},"o":{"x":[0.167],"y":[0.169]},"t":17,"s":[4.939]},{"i":{"x":[0.833],"y":[0.838]},"o":{"x":[0.167],"y":[0.17]},"t":17.5,"s":[4.339]},{"i":{"x":[0.833],"y":[0.839]},"o":{"x":[0.167],"y":[0.171]},"t":18,"s":[3.762]},{"i":{"x":[0.833],"y":[0.839]},"o":{"x":[0.167],"y":[0.172]},"t":18.5,"s":[3.215]},{"i":{"x":[0.833],"y":[0.84]},"o":{"x":[0.167],"y":[0.173]},"t":19,"s":[2.702]},{"i":{"x":[0.833],"y":[0.841]},"o":{"x":[0.167],"y":[0.174]},"t":19.5,"s":[2.227]},{"i":{"x":[0.833],"y":[0.842]},"o":{"x":[0.167],"y":[0.175]},"t":20,"s":[1.792]},{"i":{"x":[0.833],"y":[0.843]},"o":{"x":[0.167],"y":[0.176]},"t":20.5,"s":[1.397]},{"i":{"x":[0.833],"y":[0.844]},"o":{"x":[0.167],"y":[0.177]},"t":21,"s":[1.044]},{"i":{"x":[0.833],"y":[0.845]},"o":{"x":[0.167],"y":[0.179]},"t":21.5,"s":[0.73]},{"i":{"x":[0.833],"y":[0.846]},"o":{"x":[0.167],"y":[0.18]},"t":22,"s":[0.456]},{"i":{"x":[0.833],"y":[0.847]},"o":{"x":[0.167],"y":[0.181]},"t":22.5,"s":[0.219]},{"i":{"x":[0.833],"y":[0.848]},"o":{"x":[0.167],"y":[0.183]},"t":23,"s":[0.018]},{"i":{"x":[0.833],"y":[0.85]},"o":{"x":[0.167],"y":[0.185]},"t":23.5,"s":[-0.15]},{"i":{"x":[0.833],"y":[0.852]},"o":{"x":[0.167],"y":[0.188]},"t":24,"s":[-0.288]},{"i":{"x":[0.833],"y":[0.855]},"o":{"x":[0.167],"y":[0.191]},"t":24.5,"s":[-0.398]},{"i":{"x":[0.833],"y":[0.86]},"o":{"x":[0.167],"y":[0.197]},"t":25,"s":[-0.482]},{"i":{"x":[0.833],"y":[0.867]},"o":{"x":[0.167],"y":[0.206]},"t":25.5,"s":[-0.545]},{"i":{"x":[0.833],"y":[0.883]},"o":{"x":[0.167],"y":[0.224]},"t":26,"s":[-0.587]},{"i":{"x":[0.833],"y":[0.936]},"o":{"x":[0.167],"y":[0.288]},"t":26.5,"s":[-0.612]},{"i":{"x":[0.833],"y":[0.469]},"o":{"x":[0.167],"y":[-0.272]},"t":27,"s":[-0.622]},{"i":{"x":[0.833],"y":[0.778]},"o":{"x":[0.167],"y":[0.099]},"t":27.5,"s":[-0.62]},{"i":{"x":[0.833],"y":[0.807]},"o":{"x":[0.167],"y":[0.133]},"t":28,"s":[-0.607]},{"i":{"x":[0.833],"y":[0.818]},"o":{"x":[0.167],"y":[0.147]},"t":28.5,"s":[-0.586]},{"i":{"x":[0.833],"y":[0.824]},"o":{"x":[0.167],"y":[0.154]},"t":29,"s":[-0.558]},{"i":{"x":[0.833],"y":[0.828]},"o":{"x":[0.167],"y":[0.158]},"t":29.5,"s":[-0.524]},{"i":{"x":[0.833],"y":[0.83]},"o":{"x":[0.167],"y":[0.162]},"t":30,"s":[-0.488]},{"i":{"x":[0.833],"y":[0.833]},"o":{"x":[0.167],"y":[0.164]},"t":30.5,"s":[-0.448]},{"i":{"x":[0.833],"y":[0.834]},"o":{"x":[0.167],"y":[0.166]},"t":31,"s":[-0.408]},{"i":{"x":[0.833],"y":[0.833]},"o":{"x":[0.167],"y":[0.167]},"t":31.5,"s":[-0.367]},{"t":32,"s":[-0.326]}],"ix":10},"p":{"a":0,"k":[375,237.036,0],"ix":2,"l":2},"a":{"a":0,"k":[226.881,21.604,0],"ix":1,"l":2},"s":{"a":1,"k":[{"i":{"x":[0.833,0.833,0.833],"y":[1,1,1]},"o":{"x":[0.167,0.167,0.167],"y":[0,0,0]},"t":0,"s":[1644,1644,100]},{"i":{"x":[0.833,0.833,0.833],"y":[1.126,1.126,1]},"o":{"x":[0.167,0.167,0.167],"y":[0,0,0]},"t":0.5,"s":[1644,1644,100]},{"i":{"x":[0.833,0.833,0.833],"y":[0.693,0.693,1]},"o":{"x":[0.167,0.167,0.167],"y":[0.083,0.083,0]},"t":1,"s":[1644,1644,100]},{"i":{"x":[0.833,0.833,0.833],"y":[0.796,0.796,1]},"o":{"x":[0.167,0.167,0.167],"y":[0.114,0.114,0]},"t":1.5,"s":[1642.491,1642.491,100]},{"i":{"x":[0.833,0.833,0.833],"y":[0.818,0.818,1]},"o":{"x":[0.167,0.167,0.167],"y":[0.141,0.141,0]},"t":2,"s":[1638.447,1638.447,100]},{"i":{"x":[0.833,0.833,0.833],"y":[0.829,0.829,1]},"o":{"x":[0.167,0.167,0.167],"y":[0.154,0.154,0]},"t":2.5,"s":[1632.593,1632.593,100]},{"i":{"x":[0.833,0.833,0.833],"y":[0.837,0.837,1]},"o":{"x":[0.167,0.167,0.167],"y":[0.163,0.163,0]},"t":3,"s":[1625.652,1625.652,100]},{"i":{"x":[0.833,0.833,0.833],"y":[0.846,0.846,1]},"o":{"x":[0.167,0.167,0.167],"y":[0.171,0.171,0]},"t":3.5,"s":[1618.348,1618.348,100]},{"i":{"x":[0.833,0.833,0.833],"y":[0.859,0.859,1]},"o":{"x":[0.167,0.167,0.167],"y":[0.182,0.182,0]},"t":4,"s":[1611.407,1611.407,100]},{"i":{"x":[0.833,0.833,0.833],"y":[0.886,0.886,1]},"o":{"x":[0.167,0.167,0.167],"y":[0.204,0.204,0]},"t":4.5,"s":[1605.553,1605.553,100]},{"i":{"x":[0.833,0.833,0.833],"y":[1.093,1.093,1]},"o":{"x":[0.167,0.167,0.167],"y":[0.307,0.307,0]},"t":5,"s":[1601.509,1601.509,100]},{"i":{"x":[0.833,0.833,0.833],"y":[0.719,0.719,1]},"o":{"x":[0.167,0.167,0.167],"y":[0.044,0.044,0]},"t":5.5,"s":[1600,1600,100]},{"i":{"x":[0.833,0.833,0.833],"y":[0.806,0.806,1]},"o":{"x":[0.167,0.167,0.167],"y":[0.118,0.118,0]},"t":6,"s":[1603.196,1603.196,100]},{"i":{"x":[0.833,0.833,0.833],"y":[0.822,0.822,1]},"o":{"x":[0.167,0.167,0.167],"y":[0.146,0.146,0]},"t":6.5,"s":[1610.778,1610.778,100]},{"i":{"x":[0.833,0.833,0.833],"y":[0.836,0.836,1]},"o":{"x":[0.167,0.167,0.167],"y":[0.157,0.157,0]},"t":7,"s":[1620.844,1620.844,100]},{"i":{"x":[0.833,0.833,0.833],"y":[0.875,0.875,1]},"o":{"x":[0.167,0.167,0.167],"y":[0.169,0.169,0]},"t":7.5,"s":[1632.289,1632.289,100]},{"i":{"x":[0.833,0.833,0.833],"y":[0.848,0.848,1]},"o":{"x":[0.167,0.167,0.167],"y":[0.248,0.248,0]},"t":8,"s":[1643.394,1643.394,100]},{"i":{"x":[0.833,0.833,0.833],"y":[0.85,0.85,1]},"o":{"x":[0.167,0.167,0.167],"y":[0.185,0.185,0]},"t":8.5,"s":[1649.003,1649.003,100]},{"i":{"x":[0.833,0.833,0.833],"y":[0.852,0.852,1]},"o":{"x":[0.167,0.167,0.167],"y":[0.188,0.188,0]},"t":9,"s":[1653.595,1653.595,100]},{"i":{"x":[0.833,0.833,0.833],"y":[0.855,0.855,1]},"o":{"x":[0.167,0.167,0.167],"y":[0.191,0.191,0]},"t":9.5,"s":[1657.258,1657.258,100]},{"i":{"x":[0.833,0.833,0.833],"y":[0.86,0.86,1]},"o":{"x":[0.167,0.167,0.167],"y":[0.197,0.197,0]},"t":10,"s":[1660.082,1660.082,100]},{"i":{"x":[0.833,0.833,0.833],"y":[0.867,0.867,1]},"o":{"x":[0.167,0.167,0.167],"y":[0.206,0.206,0]},"t":10.5,"s":[1662.156,1662.156,100]},{"i":{"x":[0.833,0.833,0.833],"y":[0.883,0.883,1]},"o":{"x":[0.167,0.167,0.167],"y":[0.224,0.224,0]},"t":11,"s":[1663.568,1663.568,100]},{"i":{"x":[0.833,0.833,0.833],"y":[0.936,0.936,1]},"o":{"x":[0.167,0.167,0.167],"y":[0.288,0.288,0]},"t":11.5,"s":[1664.404,1664.404,100]},{"i":{"x":[0.833,0.833,0.833],"y":[0.469,0.469,1]},"o":{"x":[0.167,0.167,0.167],"y":[-0.272,-0.272,0]},"t":12,"s":[1664.744,1664.744,100]},{"i":{"x":[0.833,0.833,0.833],"y":[0.778,0.778,1]},"o":{"x":[0.167,0.167,0.167],"y":[0.099,0.099,0]},"t":12.5,"s":[1664.664,1664.664,100]},{"i":{"x":[0.833,0.833,0.833],"y":[0.807,0.807,1]},"o":{"x":[0.167,0.167,0.167],"y":[0.133,0.133,0]},"t":13,"s":[1664.236,1664.236,100]},{"i":{"x":[0.833,0.833,0.833],"y":[0.818,0.818,1]},"o":{"x":[0.167,0.167,0.167],"y":[0.147,0.147,0]},"t":13.5,"s":[1663.524,1663.524,100]},{"i":{"x":[0.833,0.833,0.833],"y":[0.824,0.824,1]},"o":{"x":[0.167,0.167,0.167],"y":[0.154,0.154,0]},"t":14,"s":[1662.588,1662.588,100]},{"i":{"x":[0.833,0.833,0.833],"y":[0.828,0.828,1]},"o":{"x":[0.167,0.167,0.167],"y":[0.158,0.158,0]},"t":14.5,"s":[1661.482,1661.482,100]},{"i":{"x":[0.833,0.833,0.833],"y":[0.83,0.83,1]},"o":{"x":[0.167,0.167,0.167],"y":[0.162,0.162,0]},"t":15,"s":[1660.253,1660.253,100]},{"i":{"x":[0.833,0.833,0.833],"y":[0.833,0.833,1]},"o":{"x":[0.167,0.167,0.167],"y":[0.164,0.164,0]},"t":15.5,"s":[1658.943,1658.943,100]},{"i":{"x":[0.833,0.833,0.833],"y":[0.834,0.834,1]},"o":{"x":[0.167,0.167,0.167],"y":[0.166,0.166,0]},"t":16,"s":[1657.589,1657.589,100]},{"i":{"x":[0.833,0.833,0.833],"y":[0.835,0.835,1]},"o":{"x":[0.167,0.167,0.167],"y":[0.167,0.167,0]},"t":16.5,"s":[1656.221,1656.221,100]},{"i":{"x":[0.833,0.833,0.833],"y":[0.837,0.837,1]},"o":{"x":[0.167,0.167,0.167],"y":[0.169,0.169,0]},"t":17,"s":[1654.866,1654.866,100]},{"i":{"x":[0.833,0.833,0.833],"y":[0.838,0.838,1]},"o":{"x":[0.167,0.167,0.167],"y":[0.17,0.17,0]},"t":17.5,"s":[1653.545,1653.545,100]},{"i":{"x":[0.833,0.833,0.833],"y":[0.839,0.839,1]},"o":{"x":[0.167,0.167,0.167],"y":[0.171,0.171,0]},"t":18,"s":[1652.276,1652.276,100]},{"i":{"x":[0.833,0.833,0.833],"y":[0.839,0.839,1]},"o":{"x":[0.167,0.167,0.167],"y":[0.172,0.172,0]},"t":18.5,"s":[1651.073,1651.073,100]},{"i":{"x":[0.833,0.833,0.833],"y":[0.84,0.84,1]},"o":{"x":[0.167,0.167,0.167],"y":[0.173,0.173,0]},"t":19,"s":[1649.945,1649.945,100]},{"i":{"x":[0.833,0.833,0.833],"y":[0.841,0.841,1]},"o":{"x":[0.167,0.167,0.167],"y":[0.174,0.174,0]},"t":19.5,"s":[1648.9,1648.9,100]},{"i":{"x":[0.833,0.833,0.833],"y":[0.842,0.842,1]},"o":{"x":[0.167,0.167,0.167],"y":[0.175,0.175,0]},"t":20,"s":[1647.942,1647.942,100]},{"i":{"x":[0.833,0.833,0.833],"y":[0.843,0.843,1]},"o":{"x":[0.167,0.167,0.167],"y":[0.176,0.176,0]},"t":20.5,"s":[1647.074,1647.074,100]},{"i":{"x":[0.833,0.833,0.833],"y":[0.844,0.844,1]},"o":{"x":[0.167,0.167,0.167],"y":[0.177,0.177,0]},"t":21,"s":[1646.296,1646.296,100]},{"i":{"x":[0.833,0.833,0.833],"y":[0.845,0.845,1]},"o":{"x":[0.167,0.167,0.167],"y":[0.179,0.179,0]},"t":21.5,"s":[1645.607,1645.607,100]},{"i":{"x":[0.833,0.833,0.833],"y":[0.846,0.846,1]},"o":{"x":[0.167,0.167,0.167],"y":[0.18,0.18,0]},"t":22,"s":[1645.004,1645.004,100]},{"i":{"x":[0.833,0.833,0.833],"y":[0.847,0.847,1]},"o":{"x":[0.167,0.167,0.167],"y":[0.181,0.181,0]},"t":22.5,"s":[1644.483,1644.483,100]},{"i":{"x":[0.833,0.833,0.833],"y":[0.848,0.848,1]},"o":{"x":[0.167,0.167,0.167],"y":[0.183,0.183,0]},"t":23,"s":[1644.04,1644.04,100]},{"i":{"x":[0.833,0.833,0.833],"y":[0.85,0.85,1]},"o":{"x":[0.167,0.167,0.167],"y":[0.185,0.185,0]},"t":23.5,"s":[1643.67,1643.67,100]},{"i":{"x":[0.833,0.833,0.833],"y":[0.852,0.852,1]},"o":{"x":[0.167,0.167,0.167],"y":[0.188,0.188,0]},"t":24,"s":[1643.367,1643.367,100]},{"i":{"x":[0.833,0.833,0.833],"y":[0.855,0.855,1]},"o":{"x":[0.167,0.167,0.167],"y":[0.191,0.191,0]},"t":24.5,"s":[1643.125,1643.125,100]},{"i":{"x":[0.833,0.833,0.833],"y":[0.86,0.86,1]},"o":{"x":[0.167,0.167,0.167],"y":[0.197,0.197,0]},"t":25,"s":[1642.939,1642.939,100]},{"i":{"x":[0.833,0.833,0.833],"y":[0.867,0.867,1]},"o":{"x":[0.167,0.167,0.167],"y":[0.206,0.206,0]},"t":25.5,"s":[1642.802,1642.802,100]},{"i":{"x":[0.833,0.833,0.833],"y":[0.883,0.883,1]},"o":{"x":[0.167,0.167,0.167],"y":[0.224,0.224,0]},"t":26,"s":[1642.709,1642.709,100]},{"i":{"x":[0.833,0.833,0.833],"y":[0.936,0.936,1]},"o":{"x":[0.167,0.167,0.167],"y":[0.288,0.288,0]},"t":26.5,"s":[1642.654,1642.654,100]},{"i":{"x":[0.833,0.833,0.833],"y":[0.469,0.469,1]},"o":{"x":[0.167,0.167,0.167],"y":[-0.272,-0.272,0]},"t":27,"s":[1642.631,1642.631,100]},{"i":{"x":[0.833,0.833,0.833],"y":[0.778,0.778,1]},"o":{"x":[0.167,0.167,0.167],"y":[0.099,0.099,0]},"t":27.5,"s":[1642.636,1642.636,100]},{"i":{"x":[0.833,0.833,0.833],"y":[0.807,0.807,1]},"o":{"x":[0.167,0.167,0.167],"y":[0.133,0.133,0]},"t":28,"s":[1642.665,1642.665,100]},{"i":{"x":[0.833,0.833,0.833],"y":[0.818,0.818,1]},"o":{"x":[0.167,0.167,0.167],"y":[0.147,0.147,0]},"t":28.5,"s":[1642.712,1642.712,100]},{"i":{"x":[0.833,0.833,0.833],"y":[0.824,0.824,1]},"o":{"x":[0.167,0.167,0.167],"y":[0.154,0.154,0]},"t":29,"s":[1642.773,1642.773,100]},{"i":{"x":[0.833,0.833,0.833],"y":[0.828,0.828,1]},"o":{"x":[0.167,0.167,0.167],"y":[0.158,0.158,0]},"t":29.5,"s":[1642.846,1642.846,100]},{"i":{"x":[0.833,0.833,0.833],"y":[0.83,0.83,1]},"o":{"x":[0.167,0.167,0.167],"y":[0.162,0.162,0]},"t":30,"s":[1642.927,1642.927,100]},{"i":{"x":[0.833,0.833,0.833],"y":[0.833,0.833,1]},"o":{"x":[0.167,0.167,0.167],"y":[0.164,0.164,0]},"t":30.5,"s":[1643.014,1643.014,100]},{"i":{"x":[0.833,0.833,0.833],"y":[0.834,0.834,1]},"o":{"x":[0.167,0.167,0.167],"y":[0.166,0.166,0]},"t":31,"s":[1643.103,1643.103,100]},{"i":{"x":[0.833,0.833,0.833],"y":[0.833,0.833,1]},"o":{"x":[0.167,0.167,0.167],"y":[0.167,0.167,0]},"t":31.5,"s":[1643.194,1643.194,100]},{"t":32,"s":[1643.283,1643.283,100]}],"ix":6,"l":2}},"ao":0,"ef":[{"ty":5,"nm":"Elastic Controller","np":5,"mn":"Pseudo/MDS Elastic Controller","ix":1,"en":1,"ef":[{"ty":0,"nm":"Amplitude","mn":"Pseudo/MDS Elastic Controller-0001","ix":1,"v":{"a":0,"k":100,"ix":1}},{"ty":0,"nm":"Frequency","mn":"Pseudo/MDS Elastic Controller-0002","ix":2,"v":{"a":0,"k":100,"ix":2}},{"ty":0,"nm":"Decay","mn":"Pseudo/MDS Elastic Controller-0003","ix":3,"v":{"a":0,"k":100,"ix":3}}]},{"ty":5,"nm":"Elastic Controller 2","np":5,"mn":"Pseudo/MDS Elastic Controller","ix":2,"en":1,"ef":[{"ty":0,"nm":"Amplitude","mn":"Pseudo/MDS Elastic Controller-0001","ix":1,"v":{"a":0,"k":100,"ix":1}},{"ty":0,"nm":"Frequency","mn":"Pseudo/MDS Elastic Controller-0002","ix":2,"v":{"a":0,"k":100,"ix":2}},{"ty":0,"nm":"Decay","mn":"Pseudo/MDS Elastic Controller-0003","ix":3,"v":{"a":0,"k":100,"ix":3}}]}],"shapes":[{"ty":"gr","it":[{"ind":0,"ty":"sh","ix":1,"ks":{"a":0,"k":{"i":[[0,3.956],[-1.229,1.229],[-3.956,0],[0,0],[-1.229,-1.229],[0,-3.956],[1.229,-1.229],[3.956,0],[0,0],[1.229,1.229]],"o":[[0,-3.956],[1.229,-1.229],[0,0],[3.956,0],[1.229,1.229],[0,3.956],[-1.229,1.229],[0,0],[-3.956,0],[-1.229,-1.229]],"v":[[-10.49,0],[-9.261,-7.163],[-2.098,-8.392],[2.098,-8.392],[9.261,-7.163],[10.49,0],[9.261,7.163],[2.098,8.392],[-2.098,8.392],[-9.261,7.163]],"c":true},"ix":2},"nm":"Path 1","mn":"ADBE Vector Shape - Group","hd":false},{"ty":"st","c":{"a":1,"k":[{"i":{"x":[0],"y":[1]},"o":{"x":[0.333],"y":[0]},"t":1,"s":[0.6,0.6,0.6,1]},{"i":{"x":[0.667],"y":[1]},"o":{"x":[1],"y":[0]},"t":9.5,"s":[0.580392181873,0.949019610882,0.498039215803,1]},{"t":18,"s":[0.6,0.6,0.6,1]}],"ix":3},"o":{"a":0,"k":100,"ix":4},"w":{"a":0,"k":2,"ix":5},"lc":1,"lj":1,"ml":4,"bm":0,"nm":"Stroke 1","mn":"ADBE Vector Graphic - Stroke","hd":false},{"ty":"tr","p":{"a":0,"k":[226.881,29.996],"ix":2},"a":{"a":0,"k":[0,0],"ix":1},"s":{"a":0,"k":[100,100],"ix":3},"r":{"a":0,"k":0,"ix":6},"o":{"a":0,"k":100,"ix":7},"sk":{"a":0,"k":0,"ix":4},"sa":{"a":0,"k":0,"ix":5},"nm":"Transform"}],"nm":"Group 2","np":2,"cix":2,"bm":0,"ix":2,"mn":"ADBE Vector Group","hd":false},{"ty":"tm","s":{"a":0,"k":0,"ix":1},"e":{"a":0,"k":100,"ix":2},"o":{"a":0,"k":69,"ix":3},"m":1,"ix":3,"nm":"Trim Paths 2","mn":"ADBE Vector Filter - Trim","hd":false}],"ip":0,"op":32,"st":0,"ct":1,"bm":0}],"markers":[],"props":{}}